typing_derive/__init__.py
typing_derive/impl.py
typing_derive/plugin.py
typing_derive-1.2.0.dist-info/LICENSE
typing_derive-1.2.0.dist-info/METADATA
typing_derive-1.2.0.dist-info/WHEEL
typing_derive-1.2.0.dist-info/top_level.txt
typing_derive-1.2.0.dist-info/RECORD
