Metadata-Version: 2.1
Name: typing_derive
Version: 1.2.0
Summary: derive types from other types to make it easier to type code!
Home-page: https://github.com/asottile/typing-derive
Author: Anthony Sottile
Author-email: asottile@umich.edu
License: MIT
Classifier: Programming Language :: Python :: 3
Classifier: Programming Language :: Python :: 3 :: Only
Classifier: Programming Language :: Python :: Implementation :: CPython
Classifier: Programming Language :: Python :: Implementation :: PyPy
Requires-Python: >=3.12
License-File: LICENSE
Provides-Extra: typing
Requires-Dist: mypy>=1.17; extra == "typing"
